Workbook

Sheet Canales
A1: ID Grupo | B1: id | C1: channel_title | D1: channel_description | E1: link | F1: channel_viewcount | G1: channel_subscribercount | H1: channel_videocount | I1: id_video | J1: recent_id_video | K1: Excluded(Nico) | L1: No se ve | M1: Sacar del grupo | N1: Sacar del inventario | O1: Comentarios | P1: Categoria
A2: 0.0 | B2: UC88zpEpyV_wQR4MXO05xf2Q | C2: Full | D2: O seu canal sobre FUTEBOL REAL e FIFA :) | E2: www.youtube.com/@fullg | F2: 486517611 | G2: 2070000 | H2: 2925 | I2: 8IP8h5RN_0U | J2: MnC68TSwDro | K2: =VLOOKUP(B2,'Excluded(Nico)'!A:A,1,False) -> #REF! | L2: TRUE | M2: FALSE | N2: TRUE | O2: La url funciona con /c/@fullg, descartar | P2: =VLOOKUP(A2,Grupos!B:E,4,FALSE) -> #REF!
A3: 0.0 | B3: UCDoOmSJp3ks_r8hbt2f0Hbw | C3: pinguinFUT | D3: Bem-vindo ao PinguinFUT jogos ao vivo assista hoje o seu canal de futebol e simulação realista fifa/pes!futebol nunca é demais, e Nunca Será demais !Aqui você acompanha os melhores momentos e gols dos principais jogos de futebol do Brasil e do Mundo.INSCREVA-SE, E ATIVE AS NOTIFICAÇÕES! conto com vocês .... | E3: www.youtube.com/@pinguinfut | F3: 58971414 | G3: 325000 | H3: 6817 | I3: cI863jYCAa8 | J3: eIOrodurpNE | K3: =VLOOKUP(B3,'Excluded(Nico)'!A:A,1,False) -> #REF! | L3: FALSE | M3: FALSE | N3: FALSE | P3: =VLOOKUP(A3,Grupos!B:E,4,FALSE) -> #REF!
A4: 0.0 | B4: UCCG1YqDMys90MUZFOLxUw5A | C4: RC Football | D4: Canal destinado aos amantes do Futebol | E4: www.youtube.com/@rcfootball | F4: 31226799 | G4: 276000 | H4: 1329 | I4: l5gNv-QzgQ0 | J4: 2QzO0-V1mQM | K4: =VLOOKUP(B4,'Excluded(Nico)'!A:A,1,False) -> #REF! | L4: FALSE | M4: FALSE | N4: FALSE | P4: =VLOOKUP(A4,Grupos!B:E,4,FALSE) -> #REF!
A5: 0.0 | B5: UCSXflBePm_wxde5_csmmUbA | C5: Santos Masinha | D5: Email para contato: santosmasinha@nwb.com.br | E5: www.youtube.com/@santosmasinha | F5: channel_viewcount | G5: 166000 | H5: 264 | I5: QbKso5BJKgE | J5: JD63rGzWec0 | K5: =VLOOKUP(B5,'Excluded(Nico)'!A:A,1,False) -> #REF! | L5: FALSE | M5: FALSE | N5: FALSE | P5: =VLOOKUP(A5,Grupos!B:E,4,FALSE) -> #REF!
A6: 0.0 | B6: UCkhrtqLk3kMI3P7sP4DUmxg | C6: Boleiros Da Firma | E6: www.youtube.com/@boleirosdafirma | F6: 10849634 | G6: 109000 | H6: 208 | I6: 5OKgS7_EE1c | J6: Mg298bI6DDY | K6: =VLOOKUP(B6,'Excluded(Nico)'!A:A,1,False) -> #REF! | L6: FALSE | M6: FALSE | N6: FALSE | P6: =VLOOKUP(A6,Grupos!B:E,4,FALSE) -> #REF!
A7: 0.0 | B7: UC8lbGIAGM0JiA_yqQw_1PBA | C7: Doug Games | D7: Welcome to DGTV, the official channel of Doug Games, here you will find:Simulations of real matches recorded in Efootball PES 2021 and FIFA 23 on PC.GameplaysLivesAll videos posted on this channel are my own, any video taken without my permission will be subject to rights claims and the channel will be penalized.- Doug Games | E7: www.youtube.com/@douggames | F7: 63289634 | G7: 264000 | H7: 5141 | I7: -5zuFSQyocc | J7: XafxZG_SkKU | K7: =VLOOKUP(B7,'Excluded(Nico)'!A:A,1,False) -> #REF! | L7: FALSE | M7: FALSE | N7: FALSE | P7: =VLOOKUP(A7,Grupos!B:E,4,FALSE) -> #REF!
A8: 0.0 | B8: UCHIY759GkSeepw6pHzVCrng | C8: Afinco | D8: Olá, meu nome é Luis mas podem me chamar de Afinco!Esse canal foi feito para você, amante do Futebol que joga e estuda Cartola FC!Espero que se divirta assistindo meus vídeos!📱 Redes Sociais do Afinco:- Procure por Afinco e vai achar 🤡(Medo do youtube diminuir o alcance blz?)✉ Contato profissional:- Contatoafinco@gmail.com | E8: www.youtube.com/@afinco | F8: 57708117 | G8: 563000 | H8: 1505 | I8: sn2i8y2rv7Q | J8: buBZJ6iuO3o | K8: =VLOOKUP(B8,'Excluded(Nico)'!A:A,1,False) -> #REF! | L8: FALSE | M8: FALSE | N8: FALSE | P8: =VLOOKUP(A8,Grupos!B:E,4,FALSE) -> #REF!
A9: 0.0 | B9: UCN3mON2F9gMRdeLZTeWrugw | C9: Campos | D9: CONTEÚDO DE EAFC 24!Email de contato: camposplay2000@gmail.com | E9: www.youtube.com/@camposplay | F9: 110081289 | G9: 334000 | H9: 4259 | I9: 5avXXHISW4I | J9: ySn2aXvlkmM | K9: =VLOOKUP(B9,'Excluded(Nico)'!A:A,1,False) -> #REF! | L9: FALSE | M9: FALSE | N9: FALSE | P9: =VLOOKUP(A9,Grupos!B:E,4,FALSE) -> #REF!
A10: 0.0 | B10: UCgoYVT-QE3rgVy8j-bT-bBQ | C10: Rick Dalas | D10: Fala rapazeada, Eu sou o Ricardo, e estou começando esse Canal com conteúdo de qualidade, meu objetivo é trazer Vídeos todos os dias, conto com o apoio de todos, e É NÒISE-MAIL COMERCIAL: rickdalas98@gmail.com | E10: www.youtube.com/@rickdalas | F10: 66264222 | G10: 464000 | H10: 521 | I10: mxYUTj5BQoU | J10: 4ju8PZOxAu8 | K10: =VLOOKUP(B10,'Excluded(Nico)'!A:A,1,False) -> #REF! | L10: FALSE | M10: FALSE | N10: FALSE | P10: =VLOOKUP(A10,Grupos!B:E,4,FALSE) -> #REF!
A11: 0.0 | B11: UCjwNVw4nFUC86eXeVb9q1NQ | C11: Hobby Games BR | D11: Olá nós somos os irmãos Hobby ! Hariston e Richard .OBJETIVOS do canal Hobby Games BR :GAMEPLAY e TUTORIAL Para ANDROID e IOS . VLOGSRikinhoHaristonAqui você verá os melhores lançamentos para ANDROID e IOS incluindo : Dream League Soccer 2020 e PES 2020 além do FIFA 2020 para android e IOS | E11: www.youtube.com/@hobbygamesr | F11: 161334 | G11: 946000 | H11: 19 | I11: 6d7BC70ATVI | J11: aaq7Eoj5JjE | K11: =VLOOKUP(B11,'Excluded(Nico)'!A:A,1,False) -> #REF! | L11: FALSE | M11: FALSE | N11: FALSE | P11: =VLOOKUP(A11,Grupos!B:E,4,FALSE) -> #REF!
A12: 0.0 | B12: UCdw7bttktkE_5pr68ODsPyg | C12: Sentimento Tricolor | D12: Canal 100% dedicado ao Fluminense Football Club e sua torcida.Sou torcedor RAIZ, acompanho o FLUMINENSE pelas arquibancadas do Brasil desde os 10 anos de idade e quero que aqui você se sinta em casa. | E12: www.youtube.com/@sentimentotricolor | F12: 53216506 | G12: 139000 | H12: 2657 | I12: Rp_QNPgGshU | J12: vn_x5CHgLMM | K12: =VLOOKUP(B12,'Excluded(Nico)'!A:A,1,False) -> #REF! | L12: FALSE | M12: FALSE | N12: FALSE | P12: =VLOOKUP(A12,Grupos!B:E,4,FALSE) -> #REF!
A13: 0.0 | B13: UCNQcv9v2nZ118drS1QI1KTw | C13: Felipe Toys | D13: Seja bem vindo ao canal do Felipe Toys, aqui você encontrará os mais diversos tipos de videos , como por exemplo desafios de futebol, brincadeiras, desafios pessoais, vlogs e muito mais. | E13: www.youtube.com/@felipetoys | F13: 348318922 | G13: 1340000 | H13: 1490 | I13: XjrDY62L_5s | J13: EEWk13fWejU | K13: =VLOOKUP(B13,'Excluded(Nico)'!A:A,1,False) -> #REF! | L13: FALSE | M13: FALSE | N13: FALSE | P13: =VLOOKUP(A13,Grupos!B:E,4,FALSE) -> #REF!
A14: 0.0 | B14: UC99MSYUyI9FH-zwhjJe7iPA | C14: EI Games | D14: Canal oficial da TNT Sports com conteúdos exclusivos de games e eSports.Nos siga também no Instagram: https://www.instagram.com/eigames/ | E14: www.youtube.com/@gamesei | F14: 83441647 | G14: 858000 | H14: 3023 | I14: 18clsiw9-LU | J14: Kmn68HBTVLo | K14: =VLOOKUP(B14,'Excluded(Nico)'!A:A,1,False) -> #REF! | L14: FALSE | M14: FALSE | N14: FALSE | P14: =VLOOKUP(A14,Grupos!B:E,4,FALSE) -> #REF!
A15: 0.0 | B15: UCGDI3T92XGq6SKH-1LSb9Fw | C15: FIFA TRADE BRASIL | D15: Este é um canal para voce que quer aprender sobre o ea fc 24 ultimate team. Aqui voce vai encontrar videos sobre, pack opening, reviews de cartas, dicas de trade, dicas para fc ultimate team, dicas de gameplay ea fc 24, novidades do ea fc 24, noticias do ea fc 24, e gameplays do ea fc 24 em geral! Se inscreve ai! | E15: www.youtube.com/@fifatradebrasil | F15: 36823603 | G15: 177000 | H15: 3366 | I15: nW7jx0ccxL8 | J15: A5NvjDGZnVo | K15: =VLOOKUP(B15,'Excluded(Nico)'!A:A,1,False) -> #REF! | L15: FALSE | M15: FALSE | N15: FALSE | P15: =VLOOKUP(A15,Grupos!B:E,4,FALSE) -> #REF!
A16: 0.0 | B16: UCq5XoJwAieUDKEx4hAnlSiw | C16: Brunelli | D16: Oi, eu sou o Brunelli, comecei no youtube em 2011 e até hoje estou tentando ser alguém na plataforma, embarque comigo nessa jornada, você será muito bem vindo.-Redes Sociais: 📸 ➡️ https://www.instagram.com/BrunelliOFC/👍🏻 ➡️ https://web.facebook.com/BrunelliOFC/✖️ ➡️ https://twitter.com/BrunelliOFC-✉ Contato Comercial ➡️ brunelli.contato@gmail.com-Quer ajudar o canal?O Pix é ➡️ brunelli.contato@gmail.com | E16: www.youtube.com/@brunelliofc | F16: 30088663 | G16: 280000 | H16: 2000 | I16: lWdUdrYutp8 | J16: doPbQKMo7RI | K16: =VLOOKUP(B16,'Excluded(Nico)'!A:A,1,False) -> #REF! | L16: FALSE | M16: FALSE | N16: FALSE | P16: =VLOOKUP(A16,Grupos!B:E,4,FALSE) -> #REF!
A17: 0.0 | B17: UCPJ_tyPCmx1tqZtInpoiwBQ | C17: Walas RDG | D17: Olá eu sou Walace conhecido como Walas RDG, Aqui vocês vão ver vídeos meus de Free Fire.Inscreva-se no canal e ativa o sininho das notificações pra não perder os próximos vídeos.Instagram: @walacerdg | E17: www.youtube.com/@walasrdg | F17: 941 | G17: 152000 | H17: 5 | I17: yJxACaiUsDA | J17: baWfBh7l_XQ | K17: =VLOOKUP(B17,'Excluded(Nico)'!A:A,1,False) -> #REF! | L17: FALSE | M17: FALSE | N17: FALSE | P17: =VLOOKUP(A17,Grupos!B:E,4,FALSE) -> #REF!
A18: 0.0 | B18: UCtE5YlcDKHKkYpoOrdC8khw | C18: FKBrasil Football | D18: Treinos Específicos para atletas de Alto Rendimento ⚽🔥INSTRAGAM OFICIAL: @timefkbr | E18: www.youtube.com/@fkbrasilfootball | F18: 27176103 | G18: 160000 | H18: 896 | I18: BZCyabYwNGc | J18: GPowUR-qpc4 | K18: =VLOOKUP(B18,'Excluded(Nico)'!A:A,1,False) -> #REF! | L18: FALSE | M18: FALSE | N18: FALSE | P18: =VLOOKUP(A18,Grupos!B:E,4,FALSE) -> #REF!
... A27: 0.0 | B27: UCJoBd1P8G8-ePHdsEyE7LyQ | C27: Boxtoker | D27: Bem vindo a Boxtoker! Canal para quem gosta de colecionáveis. Figurinhas da copa, figurinhas de free fire, figurinhas do brasileirão, cartas pokémon entre outro! | E27: www.youtube.com/@boxtoker | F27: 81127024 | G27: 337000 | H27: 403 | I27: DtzOi6mwFoo | J27: FbZaMOY_PMo | K27: =VLOOKUP(B27,'Excluded(Nico)'!A:A,1,False) -> #REF! | L27: FALSE | M27: FALSE | N27: FALSE | P27: =VLOOKUP(A27,Grupos!B:E,4,FALSE) -> #REF!
A28: 0.0 | B28: UCVBuwnAxnK97iLF10nf_f_w | C28: Pelegrino1993 | E28: www.youtube.com/@pelegrino1993_ | F28: 64278463 | G28: 133000 | H28: 3320 | I28: bZBtHP-CHvc | J28: MBlmhDrCKp4 | K28: =VLOOKUP(B28,'Excluded(Nico)'!A:A,1,False) -> #REF! | L28: FALSE | M28: FALSE | N28: FALSE | P28: =VLOOKUP(A28,Grupos!B:E,4,FALSE) -> #REF!
A29: 0.0 | B29: UCUEvQXI_xaOX_ODHmKfAdbw | C29: TL FOOTBALL | D29: BEM VINDOS AO TL FOOTBALL !! ➖➖➖➖➖➖ ✓FUTEBOL✓MEMES ✓E MUITA ZOEIRA ESPORTIVA ➖➖➖➖➖➖''NÚMERO PARA PARCERIA 81998772035 '' INSCREVA-SE E NOS AJUDE PARA O CANAL CONTINUAR CRESCENDO! | E29: www.youtube.com/@tlfootball | F29: 1453632 | G29: 97700 | H29: 113 | I29: VjT1snyqDO0 | J29: ScrYXCGA3ew | K29: =VLOOKUP(B29,'Excluded(Nico)'!A:A,1,False) -> #REF! | L29: FALSE | M29: FALSE | N29: FALSE | P29: =VLOOKUP(A29,Grupos!B:E,4,FALSE) -> #REF!
A30: 0.0 | B30: UC7Xt068bxF9Ad2qdazUixOg | C30: Arthur Zenith23 | D30: Acompanhe minhas outras redes socias!🟣 Lives - https://www.twitch.tv/arthurzenith_23📸 Instagram - https://www.instagram.com/arthurzenith/📱 TikTok - https://www.tiktok.com/@arthurzenith23 | E30: www.youtube.com/@arthurzenith23 | F30: 753606 | G30: 62300 | H30: 342 | I30: bvsXkyvToCo | J30: Z1BchbrSCa0 | K30: =VLOOKUP(B30,'Excluded(Nico)'!A:A,1,False) -> #REF! | L30: FALSE | M30: FALSE | N30: FALSE | P30: =VLOOKUP(A30,Grupos!B:E,4,FALSE) -> #REF!
A31: 0.0 | B31: UCitQqEACHHE9nibANXS4lvg | C31: KBCA FC | D31: KBCA FC CHEGANDO! Quem tá junto ta junto, quem não ta junto também tá!Opa, trazendo novidades para vocês do FIFA MOBILE e também do novo ea fc mobile, todo dia com vídeos inéditos e que vão te entreter ou te dar dicas para voar no jogo com Trades, Bugs, Dicas de gameplay e muito mais!SEJA MEMBRO DO CANAL KBCA DO FIFA ATRAVÉS DESSE LINK:/www.youtube.com/channel/UCitQqEACHHE9nibANXS4lvg/joinSe gostou do conteúdo apresentado não esquece de dar aquela fortalecida no canal se inscrevendo, deixando os likes nos vídeos, comentando e virando membro!Se você quiser participar dos grupos grátis de WhatsApp do canal, os link estão logo abaixo! | E31: www.youtube.com/@kbcafc | F31: 22794696 | G31: 144000 | H31: 1318 | I31: LIzvTIJ113s | J31: 6BlB-k0nKO0 | K31: =VLOOKUP(B31,'Excluded(Nico)'!A:A,1,False) -> #REF! | L31: FALSE | M31: FALSE | N31: FALSE | P31: =VLOOKUP(A31,Grupos!B:E,4,FALSE) -> #REF!
A32: 0.0 | B32: UCjTU4tFZX4QI8Vwym6OvLCA | C32: Leo Frannco | D32: Motivação , tutoriais e tudo sobre futebol | E32: www.youtube.com/@leo_frannco | F32: 73715048 | G32: 217000 | H32: 386 | I32: WtW8EjwqkmU | J32: TgX67XOmFds | K32: =VLOOKUP(B32,'Excluded(Nico)'!A:A,1,False) -> #REF! | L32: FALSE | M32: FALSE | N32: FALSE | P32: =VLOOKUP(A32,Grupos!B:E,4,FALSE) -> #REF!
A33: 0.0 | B33: UCYRmbP6brUZG2Urxd5175lQ | C33: Felipe Tode | D33: quer ver muitos vídeos tops de FIFA 23? esse canal então é pra você !! Meu maior objetivo é ajudar as pessoas a esquecerem os problemas do dia, e poderem relaxar um pouco assistindo alguns desafios de futebol no FIFA. Sempre tem modo carreira treinador, jogador e também experimentos.de segunda a sexta os vídeos sempre saem as 11:00 hrs da manhã (horário de Brasília) e aí, bora acompanhar alguns vídeos tops de FIFA 23? ⚽​🏆​* contato comercial fetode85@gmail.com | E33: www.youtube.com/@todegames | F33: 787067 | G33: 115000 | H33: 40 | I33: 6QQTEXk2kyo | J33: 6ePY6tOlzFg | K33: =VLOOKUP(B33,'Excluded(Nico)'!A:A,1,False) -> #REF! | L33: FALSE | M33: FALSE | N33: FALSE | P33: =VLOOKUP(A33,Grupos!B:E,4,FALSE) -> #REF!
A34: 0.0 | B34: UCc-Z1eSOmw8XV4mrZ1tIh4A | C34: CANAL DO ZÉ | D34: Canal Oficial do ex- jogador Zé Roberto, com passagens e títulos por times do Brasil, Espanha, Alemanha e Emirados Árabes.Atualmente joga na equipe do Palmeiras (Brasil).Participou de duas Copas do Mundo: a de 1998, na França; e a de 2006, na Alemanha, quando integrou a seleção do torneio eleita pela Fifa e por duas vezes foi eleito o jogador da partida.Pela Seleção Brasileira foi: Campeão da Copa América em 1997 e 1999; Campeão da Copa das Confederações em 1997 e 2005.Acumula 85 exibições pela Seleção em pouco mais de 100 convocações. | E34: www.youtube.com/zerobertoficial | F34: 2682939 | G34: 114000 | H34: 148 | I34: H77NAR34UMQ | J34: TnIY67I8C2Q | K34: =VLOOKUP(B34,'Excluded(Nico)'!A:A,1,False) -> #REF! | L34: FALSE | M34: FALSE | N34: FALSE | P34: =VLOOKUP(A34,Grupos!B:E,4,FALSE) -> #REF!
A35: 0.0 | B35: UCXaCglVjtWfADvLOTzIRqvA | C35: Deyson GamePlays | D35: Olá meus amigos!!!Este é o canal oficial do Deyson GamePlays Meu canal é sobre jogabilidade de PES e FIFA. E talvez outros jogos ...Jogos reais do canal de jogos, que se inscrevem no meu canal,Desejo-lhe felicidade e um sorriso em seus rostos! obrigado meus amigos...Instagram: @deysongameplaysYoutube: deyson gameplaysFacebook: Deyson GamePlaysEnglishHello my friends!!!This is the official Deyson GamePlays channelMy channel is about PES and FIFA gameplay. And maybe other games...Real games from gaming channel, who subscribe to my channel,I wish you happiness and a smile on your faces! thank you my friends...Instagram: @deysongameplaysYoutube: deyson gameplaysFacebook: Deyson GamePlays | E35: www.youtube.com/@deysongameplays | F35: 5111147 | G35: 36200 | H35: 5058 | I35: zakiGE5AE3E | J35: GhkBXX7WGdo | K35: =VLOOKUP(B35,'Excluded(Nico)'!A:A,1,False) -> #REF! | L35: FALSE | M35: FALSE | N35: FALSE | P35: =VLOOKUP(A35,Grupos!B:E,4,FALSE) -> #REF!
A36: 0.0 | B36: UC1EKZWVFrlfLTB_eKujc-cw | C36: MUNDO FUT REACT 2.0 | E36: www.youtube.com/@mundofut2.0 | F36: 93622 | G36: 103000 | H36: 11 | I36: MOE9n2yP-rw | J36: 469xUEeL7so | K36: =VLOOKUP(B36,'Excluded(Nico)'!A:A,1,False) -> #REF! | L36: FALSE | M36: FALSE | N36: FALSE | P36: =VLOOKUP(A36,Grupos!B:E,4,FALSE) -> #REF!
A37: 0.0 | B37: UCQ4imW50ymEBRwmk6KtjEWQ | C37: FredVasquezBR | D37: Fred Vasquez e esse é meu Canal de FIFA/Jogos de Futebol em geral. Contato Comercial: assessoria@fredvasquez.comNo meu canal você encontra jogos de FIFA, de futebol em geral e vários modos de jogo como: EA Sports FC 24, FC 24 Novidades, Reconstruindo, FIFA 23 Modo Carreira, FIFA 23 BRASILEIRÃO MOD, FIFA 23 Experimentos, FUT DRAFT, FC 24 Ultimate Team, Rages, FIFA 23 Modo Carreira Jogador, outros JOGOS DE FUTEBOL. Gosto muito também de Álbum de Figurinhas da Copa de 2022, 2018 e muito mais! | E37: www.youtube.com/@fredvasquezbr | F37: 196009300 | G37: 953000 | H37: 1611 | I37: jyAItRXfiYs | J37: ta8RHmBfc6g | K37: =VLOOKUP(B37,'Excluded(Nico)'!A:A,1,False) -> #REF! | L37: FALSE | M37: FALSE | N37: FALSE | P37: =VLOOKUP(A37,Grupos!B:E,4,FALSE) -> #REF!
A38: 0.0 | B38: UCDei52NTESecMMVgBuOneVw | C38: SMU Games | D38: O pai vem ver o icon que eu tirei!Conteúdo sobre FIFA/EA Sports FC - Pack opening, Draft, Game Play! | E38: www.youtube.com/@smugames1 | F38: 90814463 | G38: 194000 | H38: 1104 | I38: PnjiKrGlxXg | J38: JEHDNJyvzjk | K38: =VLOOKUP(B38,'Excluded(Nico)'!A:A,1,False) -> #REF! | L38: FALSE | M38: FALSE | N38: FALSE | P38: =VLOOKUP(A38,Grupos!B:E,4,FALSE) -> #REF!
A39: 0.0 | B39: UCd82LTFa0Cv1PmVnba-9oTw | C39: ALEATORIOSKU | D39: Bem-vindo ao canal aleatoriosku, o canal dedicado aos amantes de duas grandes franquias de jogos: Minecraft e Blox Fruits. Aqui você encontrará vídeos cheios de emoção, aventuras e descobertas em um universo repleto de desafios e possibilidades.Seja explorando florestas encantadas, construindo cidades impressionantes ou enfrentando inimigos poderosos, estaremos juntos nessa jornada épica pelos mundos de Minecraft e Blox Fruits. Prepare-se para se maravilhar com paisagens incríveis, conhecer personagens cativantes e aprender estratégias e dicas que vão melhorar sua experiência de jogo.Além disso, compartilhamos atualizações sobre as últimas novidades e lançamentos dos jogos, mantendo você sempre informado sobre o que está por vir.Então, junte-se a nós e embarque nessa aventura cheia de criatividade, diversão e muita emoção. Siga nosso canal no Instagram: @aleatoriosku para ficar por dentro das últimas novidades, interagir com outros fãs e participar de sorteios | E39: www.youtube.com/@aleatoriosku | F39: 70149011 | G39: 241000 | H39: 400 | I39: 1u3XrKvJR48 | J39: PIapAXBcQ2g | K39: =VLOOKUP(B39,'Excluded(Nico)'!A:A,1,False) -> #REF! | L39: FALSE | M39: FALSE | N39: FALSE | P39: =VLOOKUP(A39,Grupos!B:E,4,FALSE) -> #REF!
A40: 0.0 | B40: UCFUkISZuKPjUBoycTuzsBCA | C40: Airton Silva | D40: Vídeos de FIFA e eFootball e gameplay de outros jogos com qualidade máxima :) | E40: www.youtube.com/@airtonsilvahd | F40: 160414823 | G40: 334000 | H40: 1271 | I40: hcBuvxpCilc | J40: TQo5o7Hvd9c | K40: =VLOOKUP(B40,'Excluded(Nico)'!A:A,1,False) -> #REF! | L40: FALSE | M40: FALSE | N40: FALSE | P40: =VLOOKUP(A40,Grupos!B:E,4,FALSE) -> #REF!
A41: 0.0 | B41: UCSoFN3x2gSC2KyCl4-pwwEg | C41: BOSS FC | D41: "🔴 Sejam bem-vindos ao Boss FC, antigo FIFA Champions RJ, Lucas Boss aqui, e este é um canal focado unicamente em produzir conteúdo sobre FIFA Mobile/EA FC Mobile. Confira nossas playlists, e encontre nossas principais séries!🔵🔵🔵 INSCREVA-SE NO MEU NOVO CANAL, O ""Boss Joga Aí:"" https://bit.ly/3unoplL 🔵🔵🔵 A ""Novela do Boss"" que mostra minha evolução na conta principal, a série ""Do Zero"", onde evoluo uma conta sem gastar nada, e sem fazer trade, ""Reviews"" e ""Análise de Defensores"", lista das melhores cartas, e de carta bons e baratos nas série ""Os Melhores"" e ""Bons e Baratos"", montando times diferentes e para inscritos na série ""FCRJ Squad"", testando contas de inscrito na série ""Os Melhores Elencos dos Inscritos"", e é claro, sempre que houver eventos novos tudo sobre eles, ""Dicas para Iniciciantes"", vídeos sobre formações e muitos outros, confiram!🔴 Contato Comercial: bossfcrj.contato@gmail 🔴🔴 Contato: (19) 98973-5984 🔴🔴 Criadores: Boss Brenner e Daudt🔴 " | E41: www.youtube.com/@boss-fc | F41: 70553044 | G41: 325000 | H41: 2610 | I41: cmex3g6KZZg | J41: l9ZjhoC8Jjk | K41: =VLOOKUP(B41,'Excluded(Nico)'!A:A,1,False) -> #REF! | L41: FALSE | M41: FALSE | N41: FALSE | P41: =VLOOKUP(A41,Grupos!B:E,4,FALSE) -> #REF!
A42: 0.0 | B42: UClikilDc0QBJxQ2jZXOYg0g | C42: Wendelllira11 | D42: Wendell Silva Lira, natural de Goiânia, nascido em 7 de janeiro de 1989, ex-futebolista profissional, ganhador do Prêmio Puskás de 2015-16, aos 27 anos de idade. Atualmente, streamer e pro player de Fifa pelo FLUXO na categoria de eSports. | E42: www.youtube.com/@wendelllira11 | F42: 70844345 | G42: 255000 | H42: 988 | I42: lxYMgxfLGjo | J42: -xeTkOI4OOY | K42: =VLOOKUP(B42,'Excluded(Nico)'!A:A,1,False) -> #REF! | L42: FALSE | M42: FALSE | N42: FALSE | P42: =VLOOKUP(A42,Grupos!B:E,4,FALSE) -> #REF!
A43: 0.0 | B43: UCrkSOd8m17PJK5yQ6RoFa6A | C43: RAFÃO | D43: Um pouco de Free Fire, jogos aleatórios e vlogs...Contato: rafao@krew.ggINSTAGRAM - @rafaotv | E43: www.youtube.com/@rafao_tv | F43: 447232048 | G43: 4490000 | H43: 1251 | I43: BBSLJq9DSqY | J43: K4dbeZT34QI | K43: =VLOOKUP(B43,'Excluded(Nico)'!A:A,1,False) -> #REF! | L43: FALSE | M43: FALSE | N43: FALSE | P43: =VLOOKUP(A43,Grupos!B:E,4,FALSE) -> #REF!
A44: 0.0 | B44: UCfKPSbHBWiUeYKFPlurpy9g | C44: Rodrigol FC | D44: Um canal de um viciado em FIFA, usuário de packs, apreciador dos dribles 5 estrelas e que adora chutar uma bola do meio da rua. Bora fazer gol comigo? | E44: www.youtube.com/@rodrigolfc | F44: 12341267 | G44: 124000 | H44: 682 | I44: scf_RRmWt8Y | J44: pAKP2-h0f2I | K44: =VLOOKUP(B44,'Excluded(Nico)'!A:A,1,False) -> #REF! | L44: FALSE | M44: FALSE | N44: FALSE | P44: =VLOOKUP(A44,Grupos!B:E,4,FALSE) -> #REF!
A45: 0.0 | B45: UCxKT_vmelBGqcpy1pya4nVQ | C45: morais jose | D45: FUTEBOL TOTAL (Morais José) - não sei qual critério que eles usam podemos perder um trabalho dedicado a todos vcs garanto eu sem nem um fim lucrativo só por diversão, eles notificam videos de um canal e outro não por isso digo não sei o critério. E mais videos com mais de ano que foi postado. vamos tentar seguir ok...TOTAL FOOTBALL (Morais José) - do not know what criteria they use may lose dedicated to all you guys I assure work without even making a profit just for fun, they notify videos from a channel and another not so I say do not know the criteria. And more videos over the year that was posted. ok ... let's try to followFÚTBOL TOTAL (Morais José) - no saben cuáles son los criterios que utilizan pueden perder dedicado a todos ustedes me aseguro de trabajo sin siquiera hacer un beneficio sólo por diversión, notifiquen los videos de un canal y el otro no, así que digo no conocen los criterios. Y más vídeos sobre el año en que fue publicado. ok ... vamos a tratar de seguir | E45: www.youtube.com/@moraisjose3312 | F45: 40788249 | G45: 98000 | H45: 1180 | I45: VmzwayCpbdw | J45: atE10bCUiY4 | K45: =VLOOKUP(B45,'Excluded(Nico)'!A:A,1,False) -> #REF! | L45: FALSE | M45: FALSE | N45: FALSE | P45: =VLOOKUP(A45,Grupos!B:E,4,FALSE) -> #REF!
A46: 0.0 | B46: UC2MZiyGuWl_w5FC2iF50hcA | C46: NOTAG | D46: 📩 Contato para parcerias e divulgações: notaggames@gmail.comMe siga em todas as redes sociais: @NotagFut | E46: www.youtube.com/@notagfut | F46: 57387592 | G46: 260000 | H46: 3629 | I46: jdwd48gRdaI | J46: DlAZMNDPD1M | K46: =VLOOKUP(B46,'Excluded(Nico)'!A:A,1,False) -> #REF! | L46: FALSE | M46: FALSE | N46: FALSE | P46: =VLOOKUP(A46,Grupos!B:E,4,FALSE) -> #REF!
A47: 0.0 | B47: UCiEyRxTPlsTg5hf6brK8S0A | C47: Higor Kamui | D47: Vídeos diários de Fifa MobileMais informações e redes sociais no meu Instagram @higorkamui | E47: www.youtube.com/@higorkamuii | F47: 197338851 | G47: 424000 | H47: 524 | I47: OWapKXHPPa8 | J47: -tmXmh9ereQ | K47: =VLOOKUP(B47,'Excluded(Nico)'!A:A,1,False) -> #REF! | L47: FALSE | M47: FALSE | N47: FALSE | P47: =VLOOKUP(A47,Grupos!B:E,4,FALSE) -> #REF!
A48: 0.0 | B48: UCVFzA6CL2m2Bvi5tyWWF_Mw | C48: Frankson BR | D48: Salve família🎮 sejam todos bem vindos ao nosso canal de FREE FIRE (GARENA) & de FC MOBILE ( FIFA) aqui você encontra vídeos curtos do Free Fire e conteúdos longos do Fifa... Espero que vocês curtam o canal Tmj sempre👍🏻❤️#rumoa100k🙏Me segue no instagram: @frankson__brReflexão...Quando você vencer na vida nunca esqueça de quem te apoiou! e o principal de tudo, nunca se esqueça de Deus! pois ele foi e sempre será o único que te apoiou de verdade na sua conquista, o único que não zombou de vc pelas costas quando vc estava correndo atrás dos seus sonhos q pra muitos era loucura! | E48: www.youtube.com/@franksonbr | F48: 6352717 | G48: 144000 | H48: 982 | I48: wyoYvkZFgWs | J48: Rv9S6fFqh-w | K48: =VLOOKUP(B48,'Excluded(Nico)'!A:A,1,False) -> #REF! | L48: FALSE | M48: FALSE | N48: FALSE | P48: =VLOOKUP(A48,Grupos!B:E,4,FALSE) -> #REF!
... A64: 0.0 | B64: UCrJrTuNyaYgjFh8aNHzCLuQ | C64: Linker | D64: Canal focado em jogos e assuntos relacionados ao futebol mas as vezes pode rolar umas zoeiras sobre outros assuntos/jogos! espero que gostem!💰 Fifa coins com agilidade e segurança no maior site das Américas ⬇️Loja https://bit.ly/3eDlIuaEconomize 5% utilizando o cupom Linker | E64: www.youtube.com/@irlandolinker | F64: 80025120 | G64: 229000 | H64: 6377 | I64: jyeZ4GaHpWs | J64: czig5NmMDLQ | K64: =VLOOKUP(B64,'Excluded(Nico)'!A:A,1,False) -> #REF! | L64: FALSE | M64: FALSE | N64: FALSE | P64: =VLOOKUP(A64,Grupos!B:E,4,FALSE) -> #REF!
A65: 0.0 | B65: UCEcj3ACFdXPn2OaNZUSholQ | C65: Miguel do Fortnite | E65: www.youtube.com/@migueldofortnite | F65: 18544323 | G65: 102000 | H65: 107 | I65: 2K8YZZBIHKw | J65: 2TnRvUMbp-s | K65: =VLOOKUP(B65,'Excluded(Nico)'!A:A,1,False) -> #REF! | L65: FALSE | M65: FALSE | N65: FALSE | P65: =VLOOKUP(A65,Grupos!B:E,4,FALSE) -> #REF!
A66: 0.0 | B66: UCJHo5gxHgtrh4ZK1GIYfXng | C66: FIFA TRADE CHANNEL | D66: Bem vindo ao FIFA TRADE CHANNEL - EA SPORTS FC / EAFC 24 / #EASPORTSFC #FC24WHATSAPP: +5511986176770 - mensagem.Instagram/Twitter: @FIFATRADECHANN1GRUPO GRÁTIS: https://t.me/FIFATRADECHANN1Aqui vc encontrará informações acerca de: DICA DE TRADE EAFC24 / EAFC , ULTIMATE TEAM FC , MELHOR ELENCO , TOTY TOTS EVENTO EA FC , COMO GANHAR COINS NO EAFC UT , GRUPO DE TRADE , WEB APP , COMO FAZER TRADE , MELHORES JOGADORES TRADE , COMPANION Inscreva-se neste Canal e fique ligado às novidades.Ah! Por favor, ajude este Canal crescer, compartilhando com seus amigos!Bom divertimento!________________________________________________________________Welcome to FIFA TRADE CHANNEL - BRASILHere you will find dozens of videos related to video game play from EA Sports FC 24 and other versions , trades tips in Ultimate Team mode, conducted online matches ( seasons clubs UT etc.) , pack opening , etc.Sign and stay tuned for news !!! | E66: www.youtube.com/@fifatradechann1 | F66: 6871843 | G66: 99500 | H66: 1931 | I66: MCIALNHn4Qg | J66: TN5a1enuJ3Y | K66: =VLOOKUP(B66,'Excluded(Nico)'!A:A,1,False) -> #REF! | L66: FALSE | M66: FALSE | N66: FALSE | P66: =VLOOKUP(A66,Grupos!B:E,4,FALSE) -> #REF!
A67: 0.0 | B67: UCKTZKPG3qeFd48vDNG2Fh_Q | C67: rc97 football | D67: *Aqui você encontra*LANCES ESPETACULARES QUE ACONTECEM NO MUNDO DO FUTEBOL E CURIOSIDADES | E67: www.youtube.com/@rc97football | F67: 380414 | G67: 218000 | H67: 20 | I67: ypbECOWON7Y | J67: FqT2lPPDRNU | K67: =VLOOKUP(B67,'Excluded(Nico)'!A:A,1,False) -> #REF! | L67: FALSE | M67: FALSE | N67: FALSE | P67: =VLOOKUP(A67,Grupos!B:E,4,FALSE) -> #REF!
A68: 0.0 | B68: UCRrqdOG8U12WecJpW2orGrA | C68: Lucas Cordeiro | D68: ⭐Aqui você vai encontrar muito conteúdo de EA SPORTS FC, FIFA, Efootball e outros games de futebol. Sinta-se a vontade para se inscrever no canal e dar aquela força dando like nos videos. Muito Obrigado.⭐Me siga nas outras redes:www.instagram.com/lucasdscordeirowww.tiktok.com/lucasdscordeirowww.discord.gg/cenouroswww.twitter.com/lucasdscordeiro⭐Contato para parceriasmarcelo@m2bpro.com.br#lucascordeiro #fifa23 #efootball #futdraft #reels #ultimateteam | E68: www.youtube.com/@lucascordeiro | F68: 1061422395 | G68: 2580000 | H68: 4323 | I68: Pt-G7-oJ1yo | J68: 8tFum0B9qoY | K68: =VLOOKUP(B68,'Excluded(Nico)'!A:A,1,False) -> #REF! | L68: FALSE | M68: FALSE | N68: FALSE | P68: =VLOOKUP(A68,Grupos!B:E,4,FALSE) -> #REF!
A69: 0.0 | B69: UCFZEKaGu08UpQZk4ODqK-KA | C69: FEULAS | D69: Um cara que faz uns vídeo de futebol, fifa, aleatoriedades e bla bla bla... | E69: www.youtube.com/@feulas | F69: 43978993 | G69: 327000 | H69: 1171 | I69: rHgHi9-Ianc | J69: FiNvdXlv5oo | K69: =VLOOKUP(B69,'Excluded(Nico)'!A:A,1,False) -> #REF! | L69: FALSE | M69: FALSE | N69: FALSE | P69: =VLOOKUP(A69,Grupos!B:E,4,FALSE) -> #REF!
A70: 0.0 | B70: UCUBWEoSo_7Ts3Rts41L4KKQ | C70: Diego Football | D70: "JESUS CRISTO É O MEU SENHOR""O Senhor é a minha rocha, a minha fortaleza e o meu libertador"" — 2 Samuel 22:2Canal com vídeos com informações das partidas do nosso Brasilzão e do Mundo" | E70: www.youtube.com/@diegofootball | F70: 8045412 | G70: 111000 | H70: 134 | I70: aGvjKctbY28 | J70: kORpHQ268FI | K70: =VLOOKUP(B70,'Excluded(Nico)'!A:A,1,False) -> #REF! | L70: FALSE | M70: FALSE | N70: FALSE | P70: =VLOOKUP(A70,Grupos!B:E,4,FALSE) -> #REF!
A71: 0.0 | B71: UCJDpEhRWe3s9H8BWuwfd9hA | C71: JL eSPORTS | D71: CANAL OFICIAL DE JOGOS MOBILE◾EFOOTBALL 2023 MOBILE◾FIFA MOBILE◾CALL OF DUTY◾ETC🎬Vídeos Novos Todos Os Dias | E71: www.youtube.com/@jlesports | F71: 109846214 | G71: 673000 | H71: 4044 | I71: C3rt8zqUu4o | J71: yQbxj4j2IUM | K71: =VLOOKUP(B71,'Excluded(Nico)'!A:A,1,False) -> #REF! | L71: FALSE | M71: FALSE | N71: FALSE | P71: =VLOOKUP(A71,Grupos!B:E,4,FALSE) -> #REF!
A72: 0.0 | B72: UCQ_ATvcbDJ-CSyNwfGUpitg | C72: Simulando FC | D72: Simulando FC é um canal de games de futebol!Aqui você vai encontrar:- Dicas e Tutoriais- Experimentos- Séries (Modo Carreira, A Jornada, etc)- Lives- E MUITO mais!Conseguimos atingir a incrível marca de 500 MIL inscritos! Muito obrigado por isso! A próxima meta é chegar nos #600K!O meu grande objetivo é ajudar. Seja com uma dica que possa mudar o seu jogo pra melhor, seja com um vídeo que te alegre, seja com uma frase que inspire. Seja como for, a meta é sempre fazer você, que assiste, feliz.E, se hoje o Simulando FC existe e cresce a cada dia, é porque somos um só. Todos os inscritos, as pessoas que me apoiam, que incentivam, que ajudam. Cada um de vocês faz parte disso!Por isso, sempre digo: #JuntosVamosLongeSimulando FC, por Fe Casalecchi | E72: www.youtube.com/@simulandofc | F72: 169288406 | G72: 567000 | H72: 1044 | I72: ZnSMDI4yfhM | J72: 3WnkE5w5W20 | K72: =VLOOKUP(B72,'Excluded(Nico)'!A:A,1,False) -> #REF! | L72: FALSE | M72: FALSE | N72: FALSE | P72: =VLOOKUP(A72,Grupos!B:E,4,FALSE) -> #REF!
A73: 0.0 | B73: UCVCN6g3PH-SvRRlNZwdU3lQ | C73: MARIOEGUIGAMER | D73: CANAL DE GAME E FUTEBOL GTA TODOS OS TIPO DE GAMER PARTIDA DE FUTEBOL SIMULADAS E COMEDIA E MUITA DIVERSÃO PARA TODOS GTA5 PES2021 FC24 TODOS OS JOGOS PRA VOCES | E73: www.youtube.com/@marioeguigamer | F73: 6689707 | G73: 134000 | H73: 4984 | I73: yiRRqp_S9CA | J73: BU2XGA5LVYA | K73: =VLOOKUP(B73,'Excluded(Nico)'!A:A,1,False) -> #REF! | L73: FALSE | M73: FALSE | N73: FALSE | P73: =VLOOKUP(A73,Grupos!B:E,4,FALSE) -> #REF!
A74: 0.0 | B74: UC_trrOWqO1dkEZYxhwraI4w | C74: opiorgamerdomundo | D74: Email para contato: milkvicz@gmail.com | E74: www.youtube.com/@opiorgamerdomundo | F74: 130538787 | G74: 614000 | H74: 3869 | I74: 32puoP_9_Ec | J74: a-RNOjBONJ8 | K74: =VLOOKUP(B74,'Excluded(Nico)'!A:A,1,False) -> #REF! | L74: FALSE | M74: FALSE | N74: FALSE | P74: =VLOOKUP(A74,Grupos!B:E,4,FALSE) -> #REF!
A75: 0.0 | B75: UCHL8vJa6ryUOgIseIO-ShbQ | C75: DL Football | D75: Seja bem vindo. Aqui você vê as notícias do futebol em primeira mão e fica muito bem atualizado. | E75: www.youtube.com/@dlfootball | F75: 41069562 | G75: 98200 | H75: 2260 | I75: tA_chunKyJY | J75: oX0O5snzD1Q | K75: =VLOOKUP(B75,'Excluded(Nico)'!A:A,1,False) -> #REF! | L75: FALSE | M75: FALSE | N75: FALSE | P75: =VLOOKUP(A75,Grupos!B:E,4,FALSE) -> #REF!
A76: 0.0 | B76: UCfaWQqPW5XC8Lpwhi0i0HXA | C76: Diegod | D76: me divirto fazendo experimentos no FIFA📧 contato: diegod.contato@gmail.com | E76: www.youtube.com/@udiegod | F76: 64513981 | G76: 221000 | H76: 93 | I76: mT8yzCo9uLs | J76: n8dsqIOIZxc | K76: =VLOOKUP(B76,'Excluded(Nico)'!A:A,1,False) -> #REF! | L76: FALSE | M76: FALSE | N76: FALSE | P76: =VLOOKUP(A76,Grupos!B:E,4,FALSE) -> #REF!
A77: 0.0 | B77: UC6Dz2zDcLLMh12sswHsRk3w | C77: Café do Setorista | D77: O canal Café do Setorista prioriza informações de bastidores do futebol e mercado da bola, especialidade do repórter Samir Carvalho, que trabalhou em grandes portais, entre eles, UOL, iG e Terra. O jornalista, que hoje é colunista no UOL, é especialista em Corinthians, mas já cobriu Santos por 15 anos, Palmeiras e São Paulo, além de coberturas in loco de Copa do Mundo, Mundial de Clubes da Fifa, no Japão, Copa Libertadores da América, Campeonato Brasileiro, Copa do Brasil, Campeonato Paulista e etc.O Café do Setorista também contém Lives, entrevistas, análise de jogos e opinião. O canal reúne duas paixões do brasileiro: futebol e café. Isso porque, além de jornalista formado, Samir Carvalho é também barista, profissional especializado em cafés de alta qualidade (especiais). Por conta disso, as lives e programas são acompanhadas de um bom café, que nunca faltou na xícara do brasileiro e, principalmente, dos setoristas que cobrem o dia a dia dos clubes. | E77: www.youtube.com/@cafedosetorista | F77: 85126763 | G77: 207000 | H77: 3197 | I77: GwnUGaTnFPo | J77: T1mD6CSb_jY | K77: =VLOOKUP(B77,'Excluded(Nico)'!A:A,1,False) -> #REF! | L77: FALSE | M77: FALSE | N77: FALSE | P77: =VLOOKUP(A77,Grupos!B:E,4,FALSE) -> #REF!
... A83: 0.0 | B83: UCKj0uuq6qeUWvaq3l6Z2WJg | C83: RB FOOTBALL | D83: CARTOLA - PALPITES - NOTÍCIAS DOS TIMES - TUDO ISSO VOCÊ ENCONTRA AQUI NO CANAL RB FOOTBALL; SE INSCREVA E NÃO PERCA NADA | E83: www.youtube.com/@rbfootball4024 | F83: 11789163 | G83: 406000 | H83: 1358 | I83: x3qgDqIFsq0 | J83: q1nzf7EaWnA | K83: =VLOOKUP(B83,'Excluded(Nico)'!A:A,1,False) -> #REF! | L83: FALSE | M83: FALSE | N83: FALSE | P83: =VLOOKUP(A83,Grupos!B:E,4,FALSE) -> #REF!
A84: 0.0 | B84: UCbg5FIZMfwWF2KscGPfCuBQ | C84: ELE NÃO DISSE ISSO | E84: www.youtube.com/elenaodisseisso | F84: 85834894 | G84: 401000 | H84: 1168 | I84: 2yYE76X9ZBI | J84: raCrJV-Qse4 | K84: =VLOOKUP(B84,'Excluded(Nico)'!A:A,1,False) -> #REF! | L84: FALSE | M84: FALSE | N84: FALSE | P84: =VLOOKUP(A84,Grupos!B:E,4,FALSE) -> #REF!
A85: 0.0 | B85: UCZD5qcen7lbLPFTjfvdLFcw | C85: Vasco TV | D85: Canal oficial do Vasco da Gama. O Gigante da Colina. | E85: www.youtube.com/@vascodagama2108 | F85: 53674865 | G85: 1310000 | H85: 715 | I85: NlHLoab6hl0 | J85: tnxrxTMd2WU | K85: =VLOOKUP(B85,'Excluded(Nico)'!A:A,1,False) -> #REF! | L85: FALSE | M85: FALSE | N85: FALSE | P85: =VLOOKUP(A85,Grupos!B:E,4,FALSE) -> #REF!
A86: 0.0 | B86: UC52YPxBsiE7Xcf_53WYXvTQ | C86: Gol Contra | D86: Somos um canal de TV, ou quase isso, onde o futebol está em PRIMEIRO lugar e o humor está em TODO lugar.FACEBOOK - www.facebook.com/contragoloficialINSTAGRAM - @golcontraoficialSNAPCHAT: golcontraTWITTER: https://twitter.com/search?q=golcontrafcContato profissional: Pedro.amaral@agencia90s.com | E86: www.youtube.com/@golcontra | F86: 88586595 | G86: 592000 | H86: 877 | I86: t4KP7xPhYoQ | J86: R8b2C5sMYW8 | K86: =VLOOKUP(B86,'Excluded(Nico)'!A:A,1,False) -> #REF! | L86: FALSE | M86: FALSE | N86: FALSE | P86: =VLOOKUP(A86,Grupos!B:E,4,FALSE) -> #REF!
A87: 0.0 | B87: UCSowRKh3a0cwCp9Flpbn_qQ | C87: Novo Neymar | D87: Os melhores cortes do canal Novo Neymar FELIPE TOYS você encontra aqui.https://www.youtube.com/channel/UCNQcv9v2nZ118drS1QI1KTw | E87: www.youtube.com/@felipetoysshorts | F87: 146760663 | G87: 384000 | H87: 629 | I87: vDoi9tGm97w | J87: qnJVxWaBsBU | K87: =VLOOKUP(B87,'Excluded(Nico)'!A:A,1,False) -> #REF! | L87: FALSE | M87: FALSE | N87: FALSE | P87: =VLOOKUP(A87,Grupos!B:E,4,FALSE) -> #REF!
A88: 0.0 | B88: UClUUD-Ol4vEW9q8kmHaBvfw | C88: Rodrigão FC | D88: Bem vindo ao meu canal, meu nome é Rodrigo Lucas e moro em Porto Alegre/RS. No canal você vai encontrar tutoriais sobre Pro Evolution Soccer, conversas sobre futebol, e dicas para mitar no cartola.Se identifica com esses assuntos? Então vem comigo! 📬 E-MAIL para contato: contato.rodrigolucasfc@yahoo.com ►REDES SOCIAIS!►Facebook Pagina: https://www.facebook.com/RodrigaoFC/►Instagram: https://www.instagram.com/rodrigolucasfc►Twitter: https://twitter.com/rodrigao92fc | E88: www.youtube.com/@rodrigaofc4333 | F88: 20043639 | G88: 128000 | H88: 680 | I88: ksbXmJt-e9E | J88: Apa6QCerUgE | K88: =VLOOKUP(B88,'Excluded(Nico)'!A:A,1,False) -> #REF! | L88: FALSE | M88: FALSE | N88: FALSE | P88: =VLOOKUP(A88,Grupos!B:E,4,FALSE) -> #REF!
A89: 0.0 | B89: UCh_E5EcMGP4FnGpqn_8VaVA | C89: Lelus Football | D89: Canal criado para postar vídeos informativos e de curiosidades sobre futebol!● Vídeos novos toda semana.● Inscreva-se para continuar recebendo vídeo.https://www.youtube.com/c/LelusFootballOfficial?sub_confirmation=1 | E89: www.youtube.com/@lelusfootball | F89: 20992286 | G89: 158000 | H89: 54 | I89: 9Klqli_xpmE | J89: 3_JPou2kuUE | K89: =VLOOKUP(B89,'Excluded(Nico)'!A:A,1,False) -> #REF! | L89: FALSE | M89: FALSE | N89: FALSE | P89: =VLOOKUP(A89,Grupos!B:E,4,FALSE) -> #REF!
A90: 0.0 | B90: UCGXRG7v0yW2WZOpP7qB5r1A | C90: INVICTUS | D90: Salve Lendas! Sejam bem-vindos ao Invictus! Neste canal teremos voltados ao FC Mobile antigo Fifa Mobile!Aqui você terá séries, lives e os melhores vídeos deste game.Se chegou a este canal e não conhece o meu canal secudário, se inscreva lá também: @multiversodoinvictusCONTATO COMERCIAL:bernardogamesdicas@gmail.com | E90: www.youtube.com/@canalinvictusyt | F90: 16273692 | G90: 97800 | H90: 1892 | I90: FS7Fm_HdrPA | J90: ev9CHPZiqAU | K90: =VLOOKUP(B90,'Excluded(Nico)'!A:A,1,False) -> #REF! | L90: FALSE | M90: FALSE | N90: FALSE | P90: =VLOOKUP(A90,Grupos!B:E,4,FALSE) -> #REF!
A91: 0.0 | B91: UCflhYB5hOiPxdjoG4EtSUKA | C91: Tode | D91: As melhores notícias do futebol você encontra aqui todos os dias !Meu maior objetivo é ajudar as pessoas a sempre ficarem a par das últimas notícias do futebol, como também as últimas transferências entre clubes, polêmicas, rumores e outras coisas do futebol. de segunda a sexta são sempre dois vídeos por dia, um ao meio dia e o segundo as 18:00 hrs (horário de Brasília) e aí, bora ficar sempre antenado em relação a esse esporte tão maravilhoso chamado futebol? ⚽​🏆​* contato comercial fetode85@gmail.com | E91: www.youtube.com/@canaldotode | F91: 310671664 | G91: 1010000 | H91: 3823 | I91: cYYykwQtQ4M | J91: L_wmwa6MaHY | K91: =VLOOKUP(B91,'Excluded(Nico)'!A:A,1,False) -> #REF! | L91: FALSE | M91: FALSE | N91: FALSE | P91: =VLOOKUP(A91,Grupos!B:E,4,FALSE) -> #REF!
A92: 0.0 | B92: UCpNVXYFwGwBRmaeQIiYig0w | C92: VARnático | D92: SOMOS UM CANAL E TIME DE STREET FOOTBALL! SEJAM BEM VINDOS, ISTO É VARnático! | E92: www.youtube.com/@varnaticofc | F92: 54096838 | G92: 135000 | H92: 1430 | I92: 5S5a1IejaNo | J92: k3UVGiOYr_g | K92: =VLOOKUP(B92,'Excluded(Nico)'!A:A,1,False) -> #REF! | L92: FALSE | M92: FALSE | N92: FALSE | P92: =VLOOKUP(A92,Grupos!B:E,4,FALSE) -> #REF!
A93: 0.0 | B93: UCS2Ww5hKnagN8n1uJQryY1g | C93: PES MIL GRAU | D93: PES MIL GRAU Canal Oficial ®Os melhores memes do futebolDeus é fiel! | E93: www.youtube.com/@pesmilgrau3878 | F93: 54506351 | G93: 503000 | H93: 45 | I93: payAqLFxplg | J93: TkNjCGdXn3A | K93: =VLOOKUP(B93,'Excluded(Nico)'!A:A,1,False) -> #REF! | L93: FALSE | M93: FALSE | N93: FALSE | P93: =VLOOKUP(A93,Grupos!B:E,4,FALSE) -> #REF!
A94: 0.0 | B94: UC0JoeUCY4kb6Q6g52N52ZrA | C94: FIFA MIL GRAU 2.0 | D94: 🇧🇷 SEJAM BEM VINDOS AO CANAL FIFA MIL GRAU!!! 🇧🇷 ⚽ MEMES DE FUTEBOL⚽ MEMES⚽ LANCES⚽ QUIZ DE FUTEBOL⚽ QUIZ SOCCER⚽ JOGOS GAMER⚽ ZUEIRA DE FUTEBOL E MUITO MAISTENHA FÉ EM DEUS E ACREDITE NOS SEUS SONHOS SEMPRE!OBRIGADO POR TUDO DEUS, POR SEMPRE REALIZAR OS MEUS SONHOS!🔔INSCREVA-SE🔔 | E94: www.youtube.com/@fifamilgrau2.0 | F94: 19040237 | G94: 129000 | H94: 319 | I94: vp6ViUjj07M | J94: 6oSPP6uS6_w | K94: =VLOOKUP(B94,'Excluded(Nico)'!A:A,1,False) -> #REF! | L94: FALSE | M94: FALSE | N94: FALSE | P94: =VLOOKUP(A94,Grupos!B:E,4,FALSE) -> #REF!
A95: 0.0 | B95: UCt7_fNkxRkhykT8_kjbjpBw | C95: AF Gameplays | D95: O canal AF Gameplays é focado em eFootball nas versões de Playstation 54, Xbox Series SX, Xbox One, PC e Mobile (Android/iOS).Vídeos do modo Dream Team o novo myClub e também tem vídeos de PES (Pro Evolution Soccer) nos modos Rumo ao Estrelato e Master League.Por aqui vai encontrar vídeos de outros jogos de futebol como EA FC, FIFA e outros games de futebol digital.Inscreva-se, ative a notificação e me siga nas rede sociais para ficar sempre atualizado.Vídeos Diários aqui no canal AF Gameplaysemail comercial: canalaf@gmail.com | E95: www.youtube.com/@afgameplaysoficial | F95: 154432090 | G95: 713000 | H95: 2688 | I95: uzqHxKwNkYk | J95: uQOpn-uMHq0 | K95: =VLOOKUP(B95,'Excluded(Nico)'!A:A,1,False) -> #REF! | L95: FALSE | M95: FALSE | N95: FALSE | P95: =VLOOKUP(A95,Grupos!B:E,4,FALSE) -> #REF!
A96: 0.0 | B96: UCMkghBv7iP8etme4qHIqkNA | C96: Double Duo | D96: Ola !!Meu nome é Felipe mas pode me chamar de Double, esse canal é voltado para jogos de futebol em geral, Dream League Soccer, FIFA e PES, em todas plataformas, video game, pc ou mobile.Contato profissional:doublecontatocomercial@gmail.com | E96: www.youtube.com/@doubleduo | F96: 22553245 | G96: 99600 | H96: 3170 | I96: H4ngy2SlwcA | J96: FeZBfCYiw50 | K96: =VLOOKUP(B96,'Excluded(Nico)'!A:A,1,False) -> #REF! | L96: FALSE | M96: FALSE | N96: FALSE | P96: =VLOOKUP(A96,Grupos!B:E,4,FALSE) -> #REF!
... A114: 0.0 | B114: UC19bWensCExYpWp00Fzh8tg | C114: Goal Fut | D114: Eu sou Edu Araujo criador e apresentador do canal GoalFut, canal de esportes com muita diversão e informação para quem ama FUTEBOL.Tudo sobre Futebol, e os principais atletas do Mundo como Messi, Cristiano Ronaldo, Neymar.Principais Clubes do Mundo e muito mais.TODA HONRA E GLÓRIA SEJA DADA À DEUS !!!GoalFut sports channel with lots of fun and information for those who love Footbal.All about Football, and leading athletes of the World like Messi, Cristiano Ronaldo, Neymar and others.Top Clubs of the World and more.GoalFut canal de deportes con mucha diversión e información para quem ama FÚTBOL.Tudo sobre Fútbol, e importantes atletas del mundo como Messi, Cristiano Ronaldo, Neymar.Principales Clubes del Mundo ... | E114: www.youtube.com/@goalfut | F114: 325447101 | G114: 1510000 | H114: 1636 | I114: lW-p6o9NGv0 | J114: o8b6HRIEOFM | K114: =VLOOKUP(B114,'Excluded(Nico)'!A:A,1,False) -> #REF! | L114: FALSE | M114: FALSE | N114: FALSE | P114: =VLOOKUP(A114,Grupos!B:E,4,FALSE) -> #REF!
A115: 0.0 | B115: UCdAubDbI93Ff-c7cvUZewjA | C115: Bruno Ferrante | E115: www.youtube.com/@brferrante | F115: 123273361 | G115: 349000 | H115: 296 | I115: uLmZEn7JW1s | J115: yIkjGBd2xzw | K115: =VLOOKUP(B115,'Excluded(Nico)'!A:A,1,False) -> #REF! | L115: FALSE | M115: FALSE | N115: FALSE | P115: =VLOOKUP(A115,Grupos!B:E,4,FALSE) -> #REF!
A116: 0.0 | B116: UC_KRkaIWrj39Pr34QPiwriw | C116: LIZEFUT - EA FC 24 | D116: LizeFUT é um jogador de EA FC 24, apaixonado pela arte de jogar futebol digital. Vídeos novos SEG, TER, QUA, QUI E SEX, sempre ao meio-dia. Contato comercial: lize@lizefut.com.br | E116: www.youtube.com/@lizefut | F116: 52779239 | G116: 319000 | H116: 2099 | I116: 1ytHv76c508 | J116: Ur1zwqGBc3k | K116: =VLOOKUP(B116,'Excluded(Nico)'!A:A,1,False) -> #REF! | L116: FALSE | M116: FALSE | N116: FALSE | P116: =VLOOKUP(A116,Grupos!B:E,4,FALSE) -> #REF!
A117: 0.0 | B117: UCRuiIF3A8n7OG-9HGaqmMpg | C117: SemiGamer | D117: Canal sobre games focado em FIFA e PES, mas trago outros conteúdos: GAMEPLAYS, TUTORIAIS, DESAFIOS DE FUTEBOL E UNBOXINGS!!Meu nome é John e sou um amante do mundo dos games! então vamos compartilhar essa paixão galera!! GamerTag XBOX ONE: imjohhn me adiciona lá ;) | E117: www.youtube.com/@semigamer | F117: 52105243 | G117: 284000 | H117: 2103 | I117: C7u45gS3BnI | J117: cN6ufxHSf24 | K117: =VLOOKUP(B117,'Excluded(Nico)'!A:A,1,False) -> #REF! | L117: FALSE | M117: FALSE | N117: FALSE | P117: =VLOOKUP(A117,Grupos!B:E,4,FALSE) -> #REF!
A118: 0.0 | B118: UCAnCxJ1Weh2pUAKJW0bro0Q | C118: Paramount+ Brasil | D118: Modo férias tá ON com a minha DIRETORIA! 🔥 #DeFériasDiretoria já está disponível no meu app! | E118: www.youtube.com/@paramountplusbr | F118: 118292397 | G118: 454000 | H118: 1898 | I118: obDaxijXmt8 | J118: iZGXq2A3JV8 | K118: =VLOOKUP(B118,'Excluded(Nico)'!A:A,1,False) -> #REF! | L118: FALSE | M118: FALSE | N118: TRUE | P118: =VLOOKUP(A118,Grupos!B:E,4,FALSE) -> #REF!
A119: 0.0 | B119: UCmxLhQcyRE_kmUyZyVT9syg | C119: Léo Gamer Mobile | D119: INSCREVA SE Contato - leogamercontatodeparcerias@gmail.com | E119: www.youtube.com/@leogamermobile | F119: 6917713 | G119: 66000 | H119: 1610 | I119: tlQGoQ6mX3E | J119: uH6Q9IlgXZM | K119: =VLOOKUP(B119,'Excluded(Nico)'!A:A,1,False) -> #REF! | L119: FALSE | M119: FALSE | N119: FALSE | P119: =VLOOKUP(A119,Grupos!B:E,4,FALSE) -> #REF!
A120: 0.0 | B120: UCZYZFMLbbTA8NED2lGCb0IA | C120: DRICO GAMER | D120: Tudo bem com vocês? Eu sou o DRICO GAMER, Sou apaixonado por FUTEBOL e pelo jogo FIFA 21 da EASPORTSFIFA!Sou apresentador oficial do FIFA aqui no Brasil, e GAME CHANGERS DA EA! Seja bem vindo ao meu canal e se você curte FUTEBOL E FIFA 21 tenho certeza que vai gostar! | E120: www.youtube.com/@dricogamer | F120: 12619500 | G120: 164000 | H120: 939 | I120: jYWN5CwD-9U | J120: yMN_8JQQNVY | K120: =VLOOKUP(B120,'Excluded(Nico)'!A:A,1,False) -> #REF! | L120: FALSE | M120: FALSE | N120: FALSE | P120: =VLOOKUP(A120,Grupos!B:E,4,FALSE) -> #REF!
A121: 0.0 | B121: UCryoqZFktV5m0bo_rO3ACLw | C121: Wallyson Freestyler | D121: (INSCREVA-SE NO NOSSO CANAL ✔️✨️)(UM MUNDO DE MTT ENTRETENIMENTO 🤯💥) 《Pro de Football Freestyle ⚽️》🚀INSTAGRAM: @WALLYSON_FREESTYLEEE🎶TIKTOK: @WALLYSON_FREESTYLER 😱KWAI: @WALLYSON_FREESTYLER 🔥 VAMOS MOSTRAR PRA QUE VIEMOS 🔥Sejam Todos bem vindos ao canal!! 😍Posto videos todos os dias aqui de desafios e brincadeiras Etc...Shorts ou Vídeos Longos !!Email Pra Contato: Contato.wallysonfs@gmail.comUM V4GABUND0 SOFREDOR 🙏🏽❤ | E121: www.youtube.com/@wallysonfreestyler | F121: 131315891 | G121: 742000 | H121: 2028 | I121: i3iAc26EJXE | J121: b7yWqCEbbJ4 | K121: =VLOOKUP(B121,'Excluded(Nico)'!A:A,1,False) -> #REF! | L121: FALSE | M121: FALSE | N121: FALSE | P121: =VLOOKUP(A121,Grupos!B:E,4,FALSE) -> #REF!
A122: 1.0 | B122: UCNGi-GLrKUXz1L5Te-kA0WQ | C122: Pumuscor | D122: Bienvenido a mi canal!!! Aquí podrás disfrutar de vídeos de fútbol con los cuales te sacaré una buena sonrisa!!!Suscríbete para no perderte ningún vídeo!!!Mail de contacto profesional: Pumuscor@gmail.com | E122: www.youtube.com/@pumuscor | F122: 231246527 | G122: 904000 | H122: 3797 | I122: deskrXuHuqY | J122: 0ZURSsrSLjc | K122: =VLOOKUP(B122,'Excluded(Nico)'!A:A,1,False) -> #REF! | L122: FALSE | M122: FALSE | N122: FALSE | P122: =VLOOKUP(A122,Grupos!B:E,4,FALSE) -> #REF!
A123: 1.0 | B123: UCcgKD6aikFqg0YK872TTF9A | C123: Johan DLS | D123: Bienvenido a mi canal!En este canal encontrarán todo lo relacionado sobre el Dream League Soccer, tanto así que encontraras plantillas, mods, algunos tutoriales, y más cosas, así que si te interesa te puedes suscribir a mi canal, es totalmente gratis :D | E123: www.youtube.com/@johandls | F123: 13311022 | G123: 119000 | H123: 132 | I123: INTjiYY-rSU | J123: Kw6dfDk-L8o | K123: =VLOOKUP(B123,'Excluded(Nico)'!A:A,1,False) -> #REF! | L123: FALSE | M123: FALSE | N123: FALSE | P123: =VLOOKUP(A123,Grupos!B:E,4,FALSE) -> #REF!
A124: 1.0 | B124: UC8h85qEsJ25Os5THPu6QpHg | C124: Spursito | D124: Dosis frenéticas de diversión y algería | E124: www.youtube.com/@spursito | F124: 274954186 | G124: 1610000 | H124: 915 | I124: cooWkqj0yoQ | J124: KeL0lc9L0rE | K124: =VLOOKUP(B124,'Excluded(Nico)'!A:A,1,False) -> #REF! | L124: FALSE | M124: FALSE | N124: FALSE | P124: =VLOOKUP(A124,Grupos!B:E,4,FALSE) -> #REF!
A125: 1.0 | B125: UCcVn1CoC6sEbqZa_TfoMaEw | C125: iamSteve | D125: Aquí encontraras los mejores tops relacionados con el mundo del fútbol, no te lo pierdas!!! | E125: www.youtube.com/@steveiam | F125: 56444308 | G125: 238000 | H125: 961 | I125: 0nYW6r8H_s0 | J125: m_A32CSV6Ns | K125: =VLOOKUP(B125,'Excluded(Nico)'!A:A,1,False) -> #REF! | L125: FALSE | M125: FALSE | N125: FALSE | P125: =VLOOKUP(A125,Grupos!B:E,4,FALSE) -> #REF!
A126: 1.0 | B126: UCuyBMwuNmPTt_WUz2BdOzkA | C126: FIFAGREIFF | E126: www.youtube.com/@fifagreiff | F126: 88462445 | G126: 368000 | H126: 1459 | I126: FKu0A84x3tU | J126: PBf1tp2fNLo | K126: =VLOOKUP(B126,'Excluded(Nico)'!A:A,1,False) -> #REF! | L126: FALSE | M126: FALSE | N126: FALSE | P126: =VLOOKUP(A126,Grupos!B:E,4,FALSE) -> #REF!
A127: 1.0 | B127: UCVJ3ajHYjqyRMzU-QB0x1vA | C127: LaurixGames | D127: Malagueña a la que le gusta el FIFA y el Futbol! Si lees esto, te quiero mucho!FC24 ULTIMATE TEAM!Mil gracias por pasar!Contacto: Lauramome@gmail.com | E127: www.youtube.com/@laurixgames3409 | F127: 34089196 | G127: 106000 | H127: 1048 | I127: -mdaPmWbysI | J127: V4yK2-5JORM | K127: =VLOOKUP(B127,'Excluded(Nico)'!A:A,1,False) -> #REF! | L127: FALSE | M127: FALSE | N127: FALSE | P127: =VLOOKUP(A127,Grupos!B:E,4,FALSE) -> #REF!
A128: 1.0 | B128: UClPO7s8weRBrtPP7Pf8oqjA | C128: Edson FDB | D128: Un canal creado para todos los cracks futboleros! hacemos videos de motivacion, tutoriales, retos, gameplays y más ⚽ SUSCRIBETE►CONTACTO: edsoncastrocontacto@gmail.com | E128: www.youtube.com/@edsoncastro | F128: 910829620 | G128: 3210000 | H128: 1183 | I128: LWfXvNgNvbs | J128: FY-S7hcx5bk | K128: =VLOOKUP(B128,'Excluded(Nico)'!A:A,1,False) -> #REF! | L128: FALSE | M128: FALSE | N128: FALSE | P128: =VLOOKUP(A128,Grupos!B:E,4,FALSE) -> #REF!
A129: 1.0 | B129: UCs18BgcsY2hiGFnIo4SqW_g | C129: Xoan Ramos | D129: Soy Xoán y este es mi canal de Youtube. Tenéis vídeo de fútbol día si día no.CC de @zetagaming | E129: www.youtube.com/@xoanramos | F129: 502027541 | G129: 612000 | H129: 1016 | I129: 9HSqW_Dfr9g | J129: g34ltruVHvk | K129: =VLOOKUP(B129,'Excluded(Nico)'!A:A,1,False) -> #REF! | L129: FALSE | M129: FALSE | N129: FALSE | P129: =VLOOKUP(A129,Grupos!B:E,4,FALSE) -> #REF!
A130: 1.0 | B130: UC8vkhkX5pl9_l6c0oOHkJtQ | C130: AndrewPES | D130: Canal dedicado a las noticias y ediciones de PES, FIFA, eFootball o lo que venga. | E130: www.youtube.com/@andrewpes | F130: 22928500 | G130: 137000 | H130: 721 | I130: QjiOL6zrvxg | J130: Dv_XpZvEJnk | K130: =VLOOKUP(B130,'Excluded(Nico)'!A:A,1,False) -> #REF! | L130: FALSE | M130: FALSE | N130: FALSE | P130: =VLOOKUP(A130,Grupos!B:E,4,FALSE) -> #REF!
A131: 1.0 | B131: UCAryK8vqYoR3EOSYNjVMS0A | C131: Adri Contreras | E131: www.youtube.com/@adricontreras | F131: 434079644 | G131: 573000 | H131: 3085 | I131: kC9jcRRvG1c | J131: _yypma9V3zU | K131: =VLOOKUP(B131,'Excluded(Nico)'!A:A,1,False) -> #REF! | L131: FALSE | M131: FALSE | N131: FALSE | P131: =VLOOKUP(A131,Grupos!B:E,4,FALSE) -> #REF!
A132: 1.0 | B132: UCASyFAS0rys2xg5ofINOFOA | C132: Futbolcontemo | D132: Creador de contenido de fútbol | E132: www.youtube.com/@futbolcontemo | F132: 286253796 | G132: 375000 | H132: 2752 | I132: vUSMPphcxgg | J132: _5SqRgpR_4o | K132: =VLOOKUP(B132,'Excluded(Nico)'!A:A,1,False) -> #REF! | L132: FALSE | M132: FALSE | N132: FALSE | P132: =VLOOKUP(A132,Grupos!B:E,4,FALSE) -> #REF!
A133: 1.0 | B133: UCENsEdSphkXuvIVlfqpU-7Q | C133: papachetado | D133: codigo PAPACHETADO en la tienda de Fortnite!Merchandising Mas Chetado: https://teespring.com/es/stores/pachetotiendaA Jugar Campeon@sss!VPTBRC | E133: www.youtube.com/@papachetado | F133: 127544018 | G133: 906000 | H133: 603 | I133: cd1m41ZGsw4 | J133: 3kLGwOARPSk | K133: =VLOOKUP(B133,'Excluded(Nico)'!A:A,1,False) -> #REF! | L133: FALSE | M133: FALSE | N133: FALSE | P133: =VLOOKUP(A133,Grupos!B:E,4,FALSE) -> #REF!
A134: 1.0 | B134: UC8UZh_hNtTHGmmIJu9kxauA | C134: Crazy Crew FC | D134: El equipo de Crazy Crew FC, partidos de la liga, entrenamientos, videos de fútbol y más. | E134: www.youtube.com/@crazycrewfc | F134: 7188037 | G134: 409000 | H134: 112 | I134: IHybz-37GhA | J134: bX2kfWjEmtI | K134: =VLOOKUP(B134,'Excluded(Nico)'!A:A,1,False) -> #REF! | L134: FALSE | M134: FALSE | N134: FALSE | P134: =VLOOKUP(A134,Grupos!B:E,4,FALSE) -> #REF!
A135: 1.0 | B135: UCCfPkh8osJPC2pPq283kKXg | C135: LA COBRA | D135: Lo único que me interesa es que ruede el balón por el verde.Debate, análisis y charlas de fútbol. Canal principal.Contacto: doxen@0200.com.ar | E135: www.youtube.com/@lacobraaa | F135: 240056160 | G135: 558000 | H135: 992 | I135: 6198NdZd1Wo | J135: pU3jhNdmadY | K135: =VLOOKUP(B135,'Excluded(Nico)'!A:A,1,False) -> #REF! | L135: FALSE | M135: FALSE | N135: FALSE | P135: =VLOOKUP(A135,Grupos!B:E,4,FALSE) -> #REF!
A136: 1.0 | B136: UCXN1Ap4A1bOfNX3O4tIY_gQ | C136: xBuyer | D136: Bienvenidos a mi canal, si queréis saber más sobre este suscribiros y echarle un vistazo a mis vídeos :DEspecial 100.000 suscriptores: https://www.youtube.com/watch?v=ZVUvyGdaKvQEspecial 250.000 suscriptores: https://www.youtube.com/watch?v=rjBQMGDanKY | E136: www.youtube.com/@xbuyer | F136: 1931870126 | G136: 5620000 | H136: 1655 | I136: OLG_mMDK6dU | J136: z14tvS5HJGE | K136: =VLOOKUP(B136,'Excluded(Nico)'!A:A,1,False) -> #REF! | L136: FALSE | M136: FALSE | N136: FALSE | P136: =VLOOKUP(A136,Grupos!B:E,4,FALSE) -> #REF!
A137: 1.0 | B137: UCuRfic6fhaKEGAV7B4p4H1A | C137: El canal de Gavi | D137: ¡Bienvenidos al Canal de Gavilán!.En este canal la variedad está al gusto! Es un canal no como otro cualquiera . ¡Aquí somos de clásicos y juegazos y que mejor que traerlos en HD! ¡Este canal es simplemente para crear un ambiente enorme y amigable entre suscriptores y el canal (Osea yo) Espero que disfrutéis de vuestra estancia en el canal y qué lo disfruteis mucho ¡Haaaaasta la próxima CHAO! | E137: www.youtube.com/@elcanaldegavi | F137: 179109104 | G137: 1340000 | H137: 2594 | I137: 5MTiv9UGAhQ | J137: 9nUd9rLjkQI | K137: =VLOOKUP(B137,'Excluded(Nico)'!A:A,1,False) -> #REF! | L137: FALSE | M137: FALSE | N137: FALSE | P137: =VLOOKUP(A137,Grupos!B:E,4,FALSE) -> #REF!
A138: 1.0 | B138: UCihwgf3rrFdO5bmKhTZj7PA | C138: Jugando con los Parceros | D138: De la vida real a un videojuego, trato de recrear partidos en pes y fifa, gracias por tanto perdon por tampoco. | E138: www.youtube.com/@jugandoconlosparceros | F138: 51126298 | G138: 186000 | H138: 198 | I138: W7GByglyB4c | J138: 6Wq8dnRjR_w | K138: =VLOOKUP(B138,'Excluded(Nico)'!A:A,1,False) -> #REF! | L138: FALSE | M138: FALSE | N138: FALSE | P138: =VLOOKUP(A138,Grupos!B:E,4,FALSE) -> #REF!
A139: 1.0 | B139: UCYn15_Qzh5UrGRl97a9ni9A | C139: Miguelinhoo10 | D139: Me gusta subir FIFA y MODO CARRERA, quedate te divertiras:)Correo de contacto: miguelinhoo10negocio@hotmail.com | E139: www.youtube.com/@miguelinhoo10 | F139: 210130324 | G139: 372000 | H139: 842 | I139: OwmCS906TX0 | J139: Mj6EOx_P6dU | K139: =VLOOKUP(B139,'Excluded(Nico)'!A:A,1,False) -> #REF! | L139: FALSE | M139: FALSE | N139: FALSE | P139: =VLOOKUP(A139,Grupos!B:E,4,FALSE) -> #REF!
A140: 1.0 | B140: UCq2q6XCNa7ZozmmQMzccr0A | C140: Franklyn Gameplays | D140: Hola, mi nombre es Franklyn y este es mi canal para el Nuevo eFootball (Antes Conocido como Pro Evolution Soccer)Encontrarás:-Reviews,-Pack Opening, -Modo Cooperativo,-Curiosidades,-Creando los Mejores Equipos & Más-------------------------------------------------------------*CONTACTO SOLO PARA PUBLICIDAD*-Escribir a este Email: negociosfranklyngameplays@gmail.com--------------------------------------------------------------- | E140: www.youtube.com/@franklyngameplays | F140: 82421562 | G140: 353000 | H140: 2374 | I140: A54rlyWdS1k | J140: xhavThmafqA | K140: =VLOOKUP(B140,'Excluded(Nico)'!A:A,1,False) -> #REF! | L140: FALSE | M140: FALSE | N140: FALSE | P140: =VLOOKUP(A140,Grupos!B:E,4,FALSE) -> #REF!
A141: 1.0 | B141: UC9ocXjy9rK6zF3yUrLdiBeA | C141: Franklyn Jhonson | D141: Mi Nombre es Franklyn y Soy un Apasionado por los Videojuegos y por la Creación de Contenido, este es mi Canal Personal pero Puedes Visitarme también:-Franklyn Gameplays, -Franklyn Gameplays HD, -Frank-Frank HD -----------------------------------------------Correo para Negocios: negociosfranklyngameplays@gmail.com--------------------------------------------- | E141: www.youtube.com/@franklyn_jhonson | F141: 20820772 | G141: 157000 | H141: 289 | I141: ijGf2FhzVkk | J141: KLE6lEwBBuM | K141: =VLOOKUP(B141,'Excluded(Nico)'!A:A,1,False) -> #REF! | L141: FALSE | M141: FALSE | N141: FALSE | P141: =VLOOKUP(A141,Grupos!B:E,4,FALSE) -> #REF!
A142: 1.0 | B142: UCgipVsgFlgBVc3yOrl1vVDg | C142: SXGARRA | D142: SI ME SIGUES EN IG: SXGARRA10 ME APOYAS DE VERDAD ❤️Bienvenidos al canal oficial de Sxgarra. Creador de contenido en Tik Tok y aficionado del PSG- INSTAGRAM: https://www.instagram.com/sxgarra10/- TIKTOK: https://www.tiktok.com/@sxgarra?lang=es- TWITCH: https://www.twitch.tv/sxgarraESTA ES MI ÚNICA CUENTA OFICIAL! | E142: www.youtube.com/@sxgarra | F142: 444548193 | G142: 782000 | H142: 1742 | I142: NlNSIX-U5IQ | J142: x8E_qVQvoD8 | K142: =VLOOKUP(B142,'Excluded(Nico)'!A:A,1,False) -> #REF! | L142: FALSE | M142: FALSE | N142: FALSE | P142: =VLOOKUP(A142,Grupos!B:E,4,FALSE) -> #REF!
A143: 1.0 | B143: UCv8imGJKZ09uxEb13zxaRoA | C143: Choosey | D143: ¡Hola soy Choosey! Video diario sobre FIFA 🙂REDES SOCIALES: ⭐ TikTok: https://www.tiktok.com/@choosey_14?lang=es🟣 Twitch: https://www.twitch.tv/choosey_🔵 Twitter: https://twitter.com/Choosey_14📸 Instagram: https://www.instagram.com/choosey_14/📩 Contacto: chooseybussines@gmail.com | E143: www.youtube.com/@choosey_ | F143: 242619439 | G143: 409000 | H143: 1422 | I143: aNHZJN8G2Qk | J143: z-uTB0Qa0-A | K143: =VLOOKUP(B143,'Excluded(Nico)'!A:A,1,False) -> #REF! | L143: FALSE | M143: FALSE | N143: FALSE | P143: =VLOOKUP(A143,Grupos!B:E,4,FALSE) -> #REF!
... A162: 1.0 | B162: UC-BlQEHskwWv3a5GOiGicKw | C162: Abu | D162: Si eres amante de ULTIMATE TEAM ¡ESTE ES TU CANAL! ¡FC 24 por un tubo! Plantillas, jugadores CHETADOS y BARATOS, directos, Fut Champions, SBC´s, Division Rivals... ¡las mejores comparativas y la mejor variedad! ¿TE LO VAS A PERDER? | E162: www.youtube.com/@abuabugamerhd | F162: 42052728 | G162: 167000 | H162: 2676 | I162: 2wqP3CzqMJ8 | J162: pH7TpRBdsGs | K162: =VLOOKUP(B162,'Excluded(Nico)'!A:A,1,False) -> #REF! | L162: FALSE | M162: FALSE | N162: FALSE | P162: =VLOOKUP(A162,Grupos!B:E,4,FALSE) -> #REF!
A163: 1.0 | B163: UC-5mxbnhASzIUbu2CMjaq7A | C163: Santy Elias | E163: www.youtube.com/@santy_elias02 | F163: 533507634 | G163: 884000 | H163: 964 | I163: RCWfF8QeD14 | J163: VmDqvWIDEfs | K163: =VLOOKUP(B163,'Excluded(Nico)'!A:A,1,False) -> #REF! | L163: FALSE | M163: FALSE | N163: FALSE | P163: =VLOOKUP(A163,Grupos!B:E,4,FALSE) -> #REF!
...
